ssm_selector/__init__.py
ssm_selector/__version__.py
ssm_selector/instance_selector.py
ssm_selector/main.py
ssm_selector-0.0.1.dist-info/LICENSE
ssm_selector-0.0.1.dist-info/METADATA
ssm_selector-0.0.1.dist-info/WHEEL
ssm_selector-0.0.1.dist-info/entry_points.txt
ssm_selector-0.0.1.dist-info/RECORD
